{"groupMotions":[],"tiles":[{"y":375,"num":37,"movable":false,"group":1,"x":35.799987792969,"sheet":1},{"y":375,"num":38,"movable":false,"group":1,"x":70.099975585938,"sheet":1},{"y":375,"num":38,"movable":false,"group":1,"x":104.39996337891,"sheet":1},{"y":375,"num":38,"movable":false,"group":1,"x":138.69995117188,"sheet":1},{"y":375,"num":38,"movable":false,"group":1,"x":172.99993896484,"sheet":1},{"y":375,"num":39,"movable":false,"group":1,"x":207.29992675781,"sheet":1},{"y":355.5,"num":37,"movable":false,"group":2,"x":250.79998779297,"sheet":1},{"y":355.5,"num":38,"movable":false,"group":2,"x":285.09997558594,"sheet":1},{"y":355.5,"num":38,"movable":false,"group":2,"x":319.39996337891,"sheet":1},{"y":355.5,"num":38,"movable":false,"group":2,"x":353.69995117188,"sheet":1},{"y":355.5,"num":38,"movable":false,"group":2,"x":387.99993896484,"sheet":1},{"y":355.5,"num":39,"movable":false,"group":2,"x":422.29992675781,"sheet":1},{"y":335.5,"num":37,"movable":false,"group":3,"x":463.79998779297,"sheet":1},{"y":335.5,"num":38,"movable":false,"group":3,"x":498.09997558594,"sheet":1},{"y":335.5,"num":38,"movable":false,"group":3,"x":532.39996337891,"sheet":1},{"y":335.5,"num":38,"movable":false,"group":3,"x":566.69995117188,"sheet":1},{"y":335.5,"num":38,"movable":false,"group":3,"x":600.99993896484,"sheet":1},{"y":335.5,"num":39,"movable":false,"group":3,"x":635.29992675781,"sheet":1},{"y":314.5,"num":37,"movable":false,"group":4,"x":677.29998779297,"sheet":1},{"y":314.5,"num":38,"movable":false,"group":4,"x":711.59997558594,"sheet":1},{"y":314.5,"num":38,"movable":false,"group":4,"x":745.89996337891,"sheet":1},{"y":314.5,"num":38,"movable":false,"group":4,"x":780.19995117188,"sheet":1},{"y":314.5,"num":39,"movable":false,"group":4,"x":814.49993896484,"sheet":1},{"y":308.5,"num":3,"x":92.799987792969,"sheet":5},{"y":312,"num":37,"movable":false,"group":5,"x":923.59997558594,"sheet":1},{"y":312,"num":38,"movable":false,"group":5,"x":957.89996337891,"sheet":1},{"y":312,"num":38,"movable":false,"group":5,"x":992.19995117188,"sheet":1},{"y":312,"num":38,"movable":false,"group":5,"x":1026.5,"sheet":1},{"y":312,"num":39,"movable":false,"group":5,"x":1060.7999267578,"sheet":1},{"y":189.5,"num":1,"x":990.59997558594,"sheet":5},{"y":311,"num":37,"movable":false,"group":6,"x":1159.9000244141,"sheet":1},{"y":311,"num":38,"movable":false,"group":6,"x":1194.2000732422,"sheet":1},{"y":311,"num":38,"movable":false,"group":6,"x":1228.5001220703,"sheet":1},{"y":311,"num":38,"movable":false,"group":6,"x":1262.8001708984,"sheet":1},{"y":311,"num":39,"movable":false,"group":6,"x":1297.1002197266,"sheet":1}],"lastTrigger":0,"lastGroup":6,"properties":{"nbPieces":1,"nbRings":1,"timeMax":180},"groupDragLines":[],"energies":[{"y":331.5,"type":1,"x":185},{"y":278.5,"type":1,"x":233.5},{"y":317,"type":1,"x":277},{"y":315,"type":1,"x":399},{"y":247,"type":1,"x":434.5},{"y":284,"type":1,"x":479},{"y":282,"type":1,"x":612.5},{"y":226.5,"type":1,"x":650},{"y":265,"type":1,"x":692.5}]}